{"id":"swshp-SWSH036","name":"Arctozolt","supertype":"Pokémon","subtypes":["Stage 1"],"hp":"130","types":["Lightning"],"evolvesFrom":"Rare Fossil","abilities":[{"name":"Biting Whirlpool","text":"Whenever your opponent attaches an Energy card from their hand to 1 of their Pokémon, put 2 damage counters on that Pokémon.","type":"Ability"}],"attacks":[{"name":"Electro Ball","cost":["Lightning","Colorless"],"convertedEnergyCost":2,"damage":"70","text":""}],"weaknesses":[{"type":"Fighting","value":"×2"}],"retreatCost":["Colorless","Colorless"],"convertedRetreatCost":2,"set":{"id":"swshp","name":"SWSH Black Star Promos","series":"Sword & Shield","printedTotal":307,"total":304,"legalities":{"unlimited":"Legal","standard":"Legal","expanded":"Legal"},"ptcgoCode":"PR-SW","releaseDate":"2019/11/15","updatedAt":"2022/07/23 20:15:00","images":{"symbol":"https://images.pokemontcg.io/swshp/symbol.png","logo":"https://images.pokemontcg.io/swshp/logo.png"}},"number":"SWSH036","artist":"Hasuno","rarity":"Promo","flavorText":"The shaking of its freezing upper half is what generates its electricity. It has a hard time walking around.","nationalPokedexNumbers":[881],"legalities":{"unlimited":"Legal","expanded":"Legal"},"regulationMark":"D","images":{"small":"https://images.pokemontcg.io/swshp/SWSH036.png","large":"https://images.pokemontcg.io/swshp/SWSH036_hires.png"},"tcgplayer":{"url":"https://prices.pokemontcg.io/tcgplayer/swshp-SWSH036","updatedAt":"2023/09/16","prices":{"holofoil":{"low":27.99,"mid":31.75,"high":34.99,"market":26.91,"directLow":null}}},"cardmarket":{"url":"https://prices.pokemontcg.io/cardmarket/swshp-SWSH036","updatedAt":"2023/09/16","prices":{"averageSellPrice":12.0,"lowPrice":2.0,"trendPrice":10.24,"germanProLow":0.0,"suggestedPrice":0.0,"reverseHoloSell":0.0,"reverseHoloLow":0.0,"reverseHoloTrend":6.42,"lowPriceExPlus":2.0,"avg1":11.0,"avg7":10.5,"avg30":10.3,"reverseHoloAvg1":14.99,"reverseHoloAvg7":5.33,"reverseHoloAvg30":6.08}}}